flatten_xyz/__init__.py
flatten_xyz/exception.py
flatten_xyz/flatten.py
flatten_xyz-0.4.0.dist-info/LICENSE
flatten_xyz-0.4.0.dist-info/METADATA
flatten_xyz-0.4.0.dist-info/WHEEL
flatten_xyz-0.4.0.dist-info/top_level.txt
flatten_xyz-0.4.0.dist-info/RECORD
